{
  "docId": "lf_8156.txt",
  "sentences": [
    {
      "index": 0,
      "basicDependencies": [
        {
          "dep": "ROOT",
          "governor": 0,
          "governorGloss": "ROOT",
          "dependent": 1,
          "dependentGloss": "F"
        },
        {
          "dep": "punct",
          "governor": 1,
          "governorGloss": "F",
          "dependent": 2,
          "dependentGloss": "-"
        },
        {
          "dep": "compound",
          "governor": 9,
          "governorGloss": "A-R-T",
          "dependent": 3,
          "dependentGloss": "N"
        },
        {
          "dep": "punct",
          "governor": 9,
          "governorGloss": "A-R-T",
          "dependent": 4,
          "dependentGloss": "-"
        },
        {
          "dep": "compound",
          "governor": 9,
          "governorGloss": "A-R-T",
          "dependent": 5,
          "dependentGloss": "S"
        },
        {
          "dep": "punct",
          "governor": 9,
          "governorGloss": "A-R-T",
          "dependent": 6,
          "dependentGloss": "-"
        },
        {
          "dep": "compound",
          "governor": 9,
          "governorGloss": "A-R-T",
          "dependent": 7,
          "dependentGloss": "T"
        },
        {
          "dep": "punct",
          "governor": 9,
          "governorGloss": "A-R-T",
          "dependent": 8,
          "dependentGloss": "-"
        },
        {
          "dep": "dep",
          "governor": 1,
          "governorGloss": "F",
          "dependent": 9,
          "dependentGloss": "A-R-T"
        },
        {
          "dep": "punct",
          "governor": 1,
          "governorGloss": "F",
          "dependent": 10,
          "dependentGloss": "."
        }
      ],
      "enhancedDependencies": [
        {
          "dep": "ROOT",
          "governor": 0,
          "governorGloss": "ROOT",
          "dependent": 1,
          "dependentGloss": "F"
        },
        {
          "dep": "punct",
          "governor": 1,
          "governorGloss": "F",
          "dependent": 2,
          "dependentGloss": "-"
        },
        {
          "dep": "compound",
          "governor": 9,
          "governorGloss": "A-R-T",
          "dependent": 3,
          "dependentGloss": "N"
        },
        {
          "dep": "punct",
          "governor": 9,
          "governorGloss": "A-R-T",
          "dependent": 4,
          "dependentGloss": "-"
        },
        {
          "dep": "compound",
          "governor": 9,
          "governorGloss": "A-R-T",
          "dependent": 5,
          "dependentGloss": "S"
        },
        {
          "dep": "punct",
          "governor": 9,
          "governorGloss": "A-R-T",
          "dependent": 6,
          "dependentGloss": "-"
        },
        {
          "dep": "compound",
          "governor": 9,
          "governorGloss": "A-R-T",
          "dependent": 7,
          "dependentGloss": "T"
        },
        {
          "dep": "punct",
          "governor": 9,
          "governorGloss": "A-R-T",
          "dependent": 8,
          "dependentGloss": "-"
        },
        {
          "dep": "dep",
          "governor": 1,
          "governorGloss": "F",
          "dependent": 9,
          "dependentGloss": "A-R-T"
        },
        {
          "dep": "punct",
          "governor": 1,
          "governorGloss": "F",
          "dependent": 10,
          "dependentGloss": "."
        }
      ],
      "enhancedPlusPlusDependencies": [
        {
          "dep": "ROOT",
          "governor": 0,
          "governorGloss": "ROOT",
          "dependent": 1,
          "dependentGloss": "F"
        },
        {
          "dep": "punct",
          "governor": 1,
          "governorGloss": "F",
          "dependent": 2,
          "dependentGloss": "-"
        },
        {
          "dep": "compound",
          "governor": 9,
          "governorGloss": "A-R-T",
          "dependent": 3,
          "dependentGloss": "N"
        },
        {
          "dep": "punct",
          "governor": 9,
          "governorGloss": "A-R-T",
          "dependent": 4,
          "dependentGloss": "-"
        },
        {
          "dep": "compound",
          "governor": 9,
          "governorGloss": "A-R-T",
          "dependent": 5,
          "dependentGloss": "S"
        },
        {
          "dep": "punct",
          "governor": 9,
          "governorGloss": "A-R-T",
          "dependent": 6,
          "dependentGloss": "-"
        },
        {
          "dep": "compound",
          "governor": 9,
          "governorGloss": "A-R-T",
          "dependent": 7,
          "dependentGloss": "T"
        },
        {
          "dep": "punct",
          "governor": 9,
          "governorGloss": "A-R-T",
          "dependent": 8,
          "dependentGloss": "-"
        },
        {
          "dep": "dep",
          "governor": 1,
          "governorGloss": "F",
          "dependent": 9,
          "dependentGloss": "A-R-T"
        },
        {
          "dep": "punct",
          "governor": 1,
          "governorGloss": "F",
          "dependent": 10,
          "dependentGloss": "."
        }
      ],
      "entitymentions": [
      ],
      "tokens": [
        {
          "index": 1,
          "word": "F",
          "originalText": "F",
          "lemma": "f",
          "characterOffsetBegin": 1,
          "characterOffsetEnd": 2,
          "pos": "NN",
          "ner": "O",
          "before": " ",
          "after": ""
        },
        {
          "index": 2,
          "word": "-",
          "originalText": "-",
          "lemma": "-",
          "characterOffsetBegin": 2,
          "characterOffsetEnd": 3,
          "pos": "HYPH",
          "ner": "O",
          "before": "",
          "after": ""
        },
        {
          "index": 3,
          "word": "N",
          "originalText": "N",
          "lemma": "n",
          "characterOffsetBegin": 3,
          "characterOffsetEnd": 4,
          "pos": "NN",
          "ner": "O",
          "before": "",
          "after": ""
        },
        {
          "index": 4,
          "word": "-",
          "originalText": "-",
          "lemma": "-",
          "characterOffsetBegin": 4,
          "characterOffsetEnd": 5,
          "pos": "HYPH",
          "ner": "O",
          "before": "",
          "after": ""
        },
        {
          "index": 5,
          "word": "S",
          "originalText": "S",
          "lemma": "s",
          "characterOffsetBegin": 5,
          "characterOffsetEnd": 6,
          "pos": "NN",
          "ner": "O",
          "before": "",
          "after": ""
        },
        {
          "index": 6,
          "word": "-",
          "originalText": "-",
          "lemma": "-",
          "characterOffsetBegin": 6,
          "characterOffsetEnd": 7,
          "pos": "HYPH",
          "ner": "O",
          "before": "",
          "after": ""
        },
        {
          "index": 7,
          "word": "T",
          "originalText": "T",
          "lemma": "t",
          "characterOffsetBegin": 7,
          "characterOffsetEnd": 8,
          "pos": "NN",
          "ner": "O",
          "before": "",
          "after": ""
        },
        {
          "index": 8,
          "word": "-",
          "originalText": "-",
          "lemma": "-",
          "characterOffsetBegin": 8,
          "characterOffsetEnd": 9,
          "pos": "HYPH",
          "ner": "O",
          "before": "",
          "after": ""
        },
        {
          "index": 9,
          "word": "A-R-T",
          "originalText": "A-R-T",
          "lemma": "a-r-t",
          "characterOffsetBegin": 9,
          "characterOffsetEnd": 14,
          "pos": "NN",
          "ner": "O",
          "before": "",
          "after": ""
        },
        {
          "index": 10,
          "word": ".",
          "originalText": ".",
          "lemma": ".",
          "characterOffsetBegin": 14,
          "characterOffsetEnd": 15,
          "pos": ".",
          "ner": "O",
          "before": "",
          "after": " "
        }
      ]
    },
    {
      "index": 1,
      "basicDependencies": [
        {
          "dep": "ROOT",
          "governor": 0,
          "governorGloss": "ROOT",
          "dependent": 6,
          "dependentGloss": "E-N-D"
        },
        {
          "dep": "nummod",
          "governor": 6,
          "governorGloss": "E-N-D",
          "dependent": 1,
          "dependentGloss": "8156"
        },
        {
          "dep": "compound",
          "governor": 6,
          "governorGloss": "E-N-D",
          "dependent": 2,
          "dependentGloss": "F"
        },
        {
          "dep": "punct",
          "governor": 6,
          "governorGloss": "E-N-D",
          "dependent": 3,
          "dependentGloss": "-"
        },
        {
          "dep": "compound",
          "governor": 6,
          "governorGloss": "E-N-D",
          "dependent": 4,
          "dependentGloss": "N"
        },
        {
          "dep": "punct",
          "governor": 6,
          "governorGloss": "E-N-D",
          "dependent": 5,
          "dependentGloss": "-"
        },
        {
          "dep": "punct",
          "governor": 6,
          "governorGloss": "E-N-D",
          "dependent": 7,
          "dependentGloss": "."
        }
      ],
      "enhancedDependencies": [
        {
          "dep": "ROOT",
          "governor": 0,
          "governorGloss": "ROOT",
          "dependent": 6,
          "dependentGloss": "E-N-D"
        },
        {
          "dep": "nummod",
          "governor": 6,
          "governorGloss": "E-N-D",
          "dependent": 1,
          "dependentGloss": "8156"
        },
        {
          "dep": "compound",
          "governor": 6,
          "governorGloss": "E-N-D",
          "dependent": 2,
          "dependentGloss": "F"
        },
        {
          "dep": "punct",
          "governor": 6,
          "governorGloss": "E-N-D",
          "dependent": 3,
          "dependentGloss": "-"
        },
        {
          "dep": "compound",
          "governor": 6,
          "governorGloss": "E-N-D",
          "dependent": 4,
          "dependentGloss": "N"
        },
        {
          "dep": "punct",
          "governor": 6,
          "governorGloss": "E-N-D",
          "dependent": 5,
          "dependentGloss": "-"
        },
        {
          "dep": "punct",
          "governor": 6,
          "governorGloss": "E-N-D",
          "dependent": 7,
          "dependentGloss": "."
        }
      ],
      "enhancedPlusPlusDependencies": [
        {
          "dep": "ROOT",
          "governor": 0,
          "governorGloss": "ROOT",
          "dependent": 6,
          "dependentGloss": "E-N-D"
        },
        {
          "dep": "nummod",
          "governor": 6,
          "governorGloss": "E-N-D",
          "dependent": 1,
          "dependentGloss": "8156"
        },
        {
          "dep": "compound",
          "governor": 6,
          "governorGloss": "E-N-D",
          "dependent": 2,
          "dependentGloss": "F"
        },
        {
          "dep": "punct",
          "governor": 6,
          "governorGloss": "E-N-D",
          "dependent": 3,
          "dependentGloss": "-"
        },
        {
          "dep": "compound",
          "governor": 6,
          "governorGloss": "E-N-D",
          "dependent": 4,
          "dependentGloss": "N"
        },
        {
          "dep": "punct",
          "governor": 6,
          "governorGloss": "E-N-D",
          "dependent": 5,
          "dependentGloss": "-"
        },
        {
          "dep": "punct",
          "governor": 6,
          "governorGloss": "E-N-D",
          "dependent": 7,
          "dependentGloss": "."
        }
      ],
      "entitymentions": [
        {
          "docTokenBegin": 10,
          "docTokenEnd": 11,
          "tokenBegin": 0,
          "tokenEnd": 1,
          "text": "8156",
          "characterOffsetBegin": 16,
          "characterOffsetEnd": 20,
          "ner": "NUMBER",
          "normalizedNER": "8156.0",
          "nerConfidences": {
            "NUMBER": -1
          }
        }
      ],
      "tokens": [
        {
          "index": 1,
          "word": "8156",
          "originalText": "8156",
          "lemma": "8156",
          "characterOffsetBegin": 16,
          "characterOffsetEnd": 20,
          "pos": "CD",
          "ner": "NUMBER",
          "normalizedNER": "8156.0",
          "before": " ",
          "after": " "
        },
        {
          "index": 2,
          "word": "F",
          "originalText": "F",
          "lemma": "f",
          "characterOffsetBegin": 21,
          "characterOffsetEnd": 22,
          "pos": "NN",
          "ner": "O",
          "before": " ",
          "after": ""
        },
        {
          "index": 3,
          "word": "-",
          "originalText": "-",
          "lemma": "-",
          "characterOffsetBegin": 22,
          "characterOffsetEnd": 23,
          "pos": "HYPH",
          "ner": "O",
          "before": "",
          "after": ""
        },
        {
          "index": 4,
          "word": "N",
          "originalText": "N",
          "lemma": "n",
          "characterOffsetBegin": 23,
          "characterOffsetEnd": 24,
          "pos": "NN",
          "ner": "O",
          "before": "",
          "after": ""
        },
        {
          "index": 5,
          "word": "-",
          "originalText": "-",
          "lemma": "-",
          "characterOffsetBegin": 24,
          "characterOffsetEnd": 25,
          "pos": "HYPH",
          "ner": "O",
          "before": "",
          "after": ""
        },
        {
          "index": 6,
          "word": "E-N-D",
          "originalText": "E-N-D",
          "lemma": "e-n-d",
          "characterOffsetBegin": 25,
          "characterOffsetEnd": 30,
          "pos": "NN",
          "ner": "O",
          "before": "",
          "after": ""
        },
        {
          "index": 7,
          "word": ".",
          "originalText": ".",
          "lemma": ".",
          "characterOffsetBegin": 30,
          "characterOffsetEnd": 31,
          "pos": ".",
          "ner": "O",
          "before": "",
          "after": "  "
        }
      ]
    },
    {
      "index": 2,
      "basicDependencies": [
        {
          "dep": "ROOT",
          "governor": 0,
          "governorGloss": "ROOT",
          "dependent": 1,
          "dependentGloss": "D"
        },
        {
          "dep": "punct",
          "governor": 1,
          "governorGloss": "D",
          "dependent": 2,
          "dependentGloss": "-"
        },
        {
          "dep": "dep",
          "governor": 1,
          "governorGloss": "D",
          "dependent": 3,
          "dependentGloss": "A-T-E-S-T-A-R-T"
        },
        {
          "dep": "punct",
          "governor": 1,
          "governorGloss": "D",
          "dependent": 4,
          "dependentGloss": "."
        }
      ],
      "enhancedDependencies": [
        {
          "dep": "ROOT",
          "governor": 0,
          "governorGloss": "ROOT",
          "dependent": 1,
          "dependentGloss": "D"
        },
        {
          "dep": "punct",
          "governor": 1,
          "governorGloss": "D",
          "dependent": 2,
          "dependentGloss": "-"
        },
        {
          "dep": "dep",
          "governor": 1,
          "governorGloss": "D",
          "dependent": 3,
          "dependentGloss": "A-T-E-S-T-A-R-T"
        },
        {
          "dep": "punct",
          "governor": 1,
          "governorGloss": "D",
          "dependent": 4,
          "dependentGloss": "."
        }
      ],
      "enhancedPlusPlusDependencies": [
        {
          "dep": "ROOT",
          "governor": 0,
          "governorGloss": "ROOT",
          "dependent": 1,
          "dependentGloss": "D"
        },
        {
          "dep": "punct",
          "governor": 1,
          "governorGloss": "D",
          "dependent": 2,
          "dependentGloss": "-"
        },
        {
          "dep": "dep",
          "governor": 1,
          "governorGloss": "D",
          "dependent": 3,
          "dependentGloss": "A-T-E-S-T-A-R-T"
        },
        {
          "dep": "punct",
          "governor": 1,
          "governorGloss": "D",
          "dependent": 4,
          "dependentGloss": "."
        }
      ],
      "entitymentions": [
      ],
      "tokens": [
        {
          "index": 1,
          "word": "D",
          "originalText": "D",
          "lemma": "d",
          "characterOffsetBegin": 33,
          "characterOffsetEnd": 34,
          "pos": "NN",
          "ner": "O",
          "before": "  ",
          "after": ""
        },
        {
          "index": 2,
          "word": "-",
          "originalText": "-",
          "lemma": "-",
          "characterOffsetBegin": 34,
          "characterOffsetEnd": 35,
          "pos": ":",
          "ner": "O",
          "before": "",
          "after": ""
        },
        {
          "index": 3,
          "word": "A-T-E-S-T-A-R-T",
          "originalText": "A-T-E-S-T-A-R-T",
          "lemma": "a-t-e-s-t-a-r-t",
          "characterOffsetBegin": 35,
          "characterOffsetEnd": 50,
          "pos": "NN",
          "ner": "O",
          "before": "",
          "after": ""
        },
        {
          "index": 4,
          "word": ".",
          "originalText": ".",
          "lemma": ".",
          "characterOffsetBegin": 50,
          "characterOffsetEnd": 51,
          "pos": ".",
          "ner": "O",
          "before": "",
          "after": " "
        }
      ]
    },
    {
      "index": 3,
      "basicDependencies": [
        {
          "dep": "ROOT",
          "governor": 0,
          "governorGloss": "ROOT",
          "dependent": 4,
          "dependentGloss": "A-T-E-E-N-D"
        },
        {
          "dep": "nummod",
          "governor": 4,
          "governorGloss": "A-T-E-E-N-D",
          "dependent": 1,
          "dependentGloss": "2024-02-21"
        },
        {
          "dep": "compound",
          "governor": 4,
          "governorGloss": "A-T-E-E-N-D",
          "dependent": 2,
          "dependentGloss": "D"
        },
        {
          "dep": "punct",
          "governor": 4,
          "governorGloss": "A-T-E-E-N-D",
          "dependent": 3,
          "dependentGloss": "-"
        },
        {
          "dep": "punct",
          "governor": 4,
          "governorGloss": "A-T-E-E-N-D",
          "dependent": 5,
          "dependentGloss": "."
        }
      ],
      "enhancedDependencies": [
        {
          "dep": "ROOT",
          "governor": 0,
          "governorGloss": "ROOT",
          "dependent": 4,
          "dependentGloss": "A-T-E-E-N-D"
        },
        {
          "dep": "nummod",
          "governor": 4,
          "governorGloss": "A-T-E-E-N-D",
          "dependent": 1,
          "dependentGloss": "2024-02-21"
        },
        {
          "dep": "compound",
          "governor": 4,
          "governorGloss": "A-T-E-E-N-D",
          "dependent": 2,
          "dependentGloss": "D"
        },
        {
          "dep": "punct",
          "governor": 4,
          "governorGloss": "A-T-E-E-N-D",
          "dependent": 3,
          "dependentGloss": "-"
        },
        {
          "dep": "punct",
          "governor": 4,
          "governorGloss": "A-T-E-E-N-D",
          "dependent": 5,
          "dependentGloss": "."
        }
      ],
      "enhancedPlusPlusDependencies": [
        {
          "dep": "ROOT",
          "governor": 0,
          "governorGloss": "ROOT",
          "dependent": 4,
          "dependentGloss": "A-T-E-E-N-D"
        },
        {
          "dep": "nummod",
          "governor": 4,
          "governorGloss": "A-T-E-E-N-D",
          "dependent": 1,
          "dependentGloss": "2024-02-21"
        },
        {
          "dep": "compound",
          "governor": 4,
          "governorGloss": "A-T-E-E-N-D",
          "dependent": 2,
          "dependentGloss": "D"
        },
        {
          "dep": "punct",
          "governor": 4,
          "governorGloss": "A-T-E-E-N-D",
          "dependent": 3,
          "dependentGloss": "-"
        },
        {
          "dep": "punct",
          "governor": 4,
          "governorGloss": "A-T-E-E-N-D",
          "dependent": 5,
          "dependentGloss": "."
        }
      ],
      "entitymentions": [
        {
          "docTokenBegin": 21,
          "docTokenEnd": 22,
          "tokenBegin": 0,
          "tokenEnd": 1,
          "text": "2024-02-21",
          "characterOffsetBegin": 52,
          "characterOffsetEnd": 62,
          "ner": "DATE",
          "normalizedNER": "2024-02-21",
          "nerConfidences": {
            "DATE": -1
          },
          "timex": {
            "tid": "t1",
            "type": "DATE",
            "value": "2024-02-21"
          }
        }
      ],
      "tokens": [
        {
          "index": 1,
          "word": "2024-02-21",
          "originalText": "2024-02-21",
          "lemma": "2024-02-21",
          "characterOffsetBegin": 52,
          "characterOffsetEnd": 62,
          "pos": "CD",
          "ner": "DATE",
          "normalizedNER": "2024-02-21",
          "before": " ",
          "after": " ",
          "timex": {
            "tid": "t1",
            "type": "DATE",
            "value": "2024-02-21"
          }
        },
        {
          "index": 2,
          "word": "D",
          "originalText": "D",
          "lemma": "d",
          "characterOffsetBegin": 63,
          "characterOffsetEnd": 64,
          "pos": "NN",
          "ner": "O",
          "before": " ",
          "after": ""
        },
        {
          "index": 3,
          "word": "-",
          "originalText": "-",
          "lemma": "-",
          "characterOffsetBegin": 64,
          "characterOffsetEnd": 65,
          "pos": "HYPH",
          "ner": "O",
          "before": "",
          "after": ""
        },
        {
          "index": 4,
          "word": "A-T-E-E-N-D",
          "originalText": "A-T-E-E-N-D",
          "lemma": "a-t-e-e-n-d",
          "characterOffsetBegin": 65,
          "characterOffsetEnd": 76,
          "pos": "NN",
          "ner": "O",
          "before": "",
          "after": ""
        },
        {
          "index": 5,
          "word": ".",
          "originalText": ".",
          "lemma": ".",
          "characterOffsetBegin": 76,
          "characterOffsetEnd": 77,
          "pos": ".",
          "ner": "O",
          "before": "",
          "after": "  "
        }
      ]
    },
    {
      "index": 4,
      "basicDependencies": [
        {
          "dep": "ROOT",
          "governor": 0,
          "governorGloss": "ROOT",
          "dependent": 1,
          "dependentGloss": "T"
        },
        {
          "dep": "punct",
          "governor": 1,
          "governorGloss": "T",
          "dependent": 2,
          "dependentGloss": "-"
        },
        {
          "dep": "compound",
          "governor": 9,
          "governorGloss": "E-S-T-A-R-T",
          "dependent": 3,
          "dependentGloss": "I"
        },
        {
          "dep": "punct",
          "governor": 9,
          "governorGloss": "E-S-T-A-R-T",
          "dependent": 4,
          "dependentGloss": "-"
        },
        {
          "dep": "compound",
          "governor": 9,
          "governorGloss": "E-S-T-A-R-T",
          "dependent": 5,
          "dependentGloss": "T"
        },
        {
          "dep": "punct",
          "governor": 9,
          "governorGloss": "E-S-T-A-R-T",
          "dependent": 6,
          "dependentGloss": "-"
        },
        {
          "dep": "compound",
          "governor": 9,
          "governorGloss": "E-S-T-A-R-T",
          "dependent": 7,
          "dependentGloss": "L"
        },
        {
          "dep": "punct",
          "governor": 9,
          "governorGloss": "E-S-T-A-R-T",
          "dependent": 8,
          "dependentGloss": "-"
        },
        {
          "dep": "dep",
          "governor": 1,
          "governorGloss": "T",
          "dependent": 9,
          "dependentGloss": "E-S-T-A-R-T"
        },
        {
          "dep": "punct",
          "governor": 1,
          "governorGloss": "T",
          "dependent": 10,
          "dependentGloss": "."
        }
      ],
      "enhancedDependencies": [
        {
          "dep": "ROOT",
          "governor": 0,
          "governorGloss": "ROOT",
          "dependent": 1,
          "dependentGloss": "T"
        },
        {
          "dep": "punct",
          "governor": 1,
          "governorGloss": "T",
          "dependent": 2,
          "dependentGloss": "-"
        },
        {
          "dep": "compound",
          "governor": 9,
          "governorGloss": "E-S-T-A-R-T",
          "dependent": 3,
          "dependentGloss": "I"
        },
        {
          "dep": "punct",
          "governor": 9,
          "governorGloss": "E-S-T-A-R-T",
          "dependent": 4,
          "dependentGloss": "-"
        },
        {
          "dep": "compound",
          "governor": 9,
          "governorGloss": "E-S-T-A-R-T",
          "dependent": 5,
          "dependentGloss": "T"
        },
        {
          "dep": "punct",
          "governor": 9,
          "governorGloss": "E-S-T-A-R-T",
          "dependent": 6,
          "dependentGloss": "-"
        },
        {
          "dep": "compound",
          "governor": 9,
          "governorGloss": "E-S-T-A-R-T",
          "dependent": 7,
          "dependentGloss": "L"
        },
        {
          "dep": "punct",
          "governor": 9,
          "governorGloss": "E-S-T-A-R-T",
          "dependent": 8,
          "dependentGloss": "-"
        },
        {
          "dep": "dep",
          "governor": 1,
          "governorGloss": "T",
          "dependent": 9,
          "dependentGloss": "E-S-T-A-R-T"
        },
        {
          "dep": "punct",
          "governor": 1,
          "governorGloss": "T",
          "dependent": 10,
          "dependentGloss": "."
        }
      ],
      "enhancedPlusPlusDependencies": [
        {
          "dep": "ROOT",
          "governor": 0,
          "governorGloss": "ROOT",
          "dependent": 1,
          "dependentGloss": "T"
        },
        {
          "dep": "punct",
          "governor": 1,
          "governorGloss": "T",
          "dependent": 2,
          "dependentGloss": "-"
        },
        {
          "dep": "compound",
          "governor": 9,
          "governorGloss": "E-S-T-A-R-T",
          "dependent": 3,
          "dependentGloss": "I"
        },
        {
          "dep": "punct",
          "governor": 9,
          "governorGloss": "E-S-T-A-R-T",
          "dependent": 4,
          "dependentGloss": "-"
        },
        {
          "dep": "compound",
          "governor": 9,
          "governorGloss": "E-S-T-A-R-T",
          "dependent": 5,
          "dependentGloss": "T"
        },
        {
          "dep": "punct",
          "governor": 9,
          "governorGloss": "E-S-T-A-R-T",
          "dependent": 6,
          "dependentGloss": "-"
        },
        {
          "dep": "compound",
          "governor": 9,
          "governorGloss": "E-S-T-A-R-T",
          "dependent": 7,
          "dependentGloss": "L"
        },
        {
          "dep": "punct",
          "governor": 9,
          "governorGloss": "E-S-T-A-R-T",
          "dependent": 8,
          "dependentGloss": "-"
        },
        {
          "dep": "dep",
          "governor": 1,
          "governorGloss": "T",
          "dependent": 9,
          "dependentGloss": "E-S-T-A-R-T"
        },
        {
          "dep": "punct",
          "governor": 1,
          "governorGloss": "T",
          "dependent": 10,
          "dependentGloss": "."
        }
      ],
      "entitymentions": [
      ],
      "tokens": [
        {
          "index": 1,
          "word": "T",
          "originalText": "T",
          "lemma": "t",
          "characterOffsetBegin": 79,
          "characterOffsetEnd": 80,
          "pos": "NN",
          "ner": "O",
          "before": "  ",
          "after": ""
        },
        {
          "index": 2,
          "word": "-",
          "originalText": "-",
          "lemma": "-",
          "characterOffsetBegin": 80,
          "characterOffsetEnd": 81,
          "pos": ":",
          "ner": "O",
          "before": "",
          "after": ""
        },
        {
          "index": 3,
          "word": "I",
          "originalText": "I",
          "lemma": "i",
          "characterOffsetBegin": 81,
          "characterOffsetEnd": 82,
          "pos": "NN",
          "ner": "O",
          "before": "",
          "after": ""
        },
        {
          "index": 4,
          "word": "-",
          "originalText": "-",
          "lemma": "-",
          "characterOffsetBegin": 82,
          "characterOffsetEnd": 83,
          "pos": "HYPH",
          "ner": "O",
          "before": "",
          "after": ""
        },
        {
          "index": 5,
          "word": "T",
          "originalText": "T",
          "lemma": "t",
          "characterOffsetBegin": 83,
          "characterOffsetEnd": 84,
          "pos": "NN",
          "ner": "O",
          "before": "",
          "after": ""
        },
        {
          "index": 6,
          "word": "-",
          "originalText": "-",
          "lemma": "-",
          "characterOffsetBegin": 84,
          "characterOffsetEnd": 85,
          "pos": "HYPH",
          "ner": "O",
          "before": "",
          "after": ""
        },
        {
          "index": 7,
          "word": "L",
          "originalText": "L",
          "lemma": "l",
          "characterOffsetBegin": 85,
          "characterOffsetEnd": 86,
          "pos": "NN",
          "ner": "O",
          "before": "",
          "after": ""
        },
        {
          "index": 8,
          "word": "-",
          "originalText": "-",
          "lemma": "-",
          "characterOffsetBegin": 86,
          "characterOffsetEnd": 87,
          "pos": "HYPH",
          "ner": "O",
          "before": "",
          "after": ""
        },
        {
          "index": 9,
          "word": "E-S-T-A-R-T",
          "originalText": "E-S-T-A-R-T",
          "lemma": "e-s-t-a-r-t",
          "characterOffsetBegin": 87,
          "characterOffsetEnd": 98,
          "pos": "NN",
          "ner": "O",
          "before": "",
          "after": ""
        },
        {
          "index": 10,
          "word": ".",
          "originalText": ".",
          "lemma": ".",
          "characterOffsetBegin": 98,
          "characterOffsetEnd": 99,
          "pos": ".",
          "ner": "O",
          "before": "",
          "after": " "
        }
      ]
    },
    {
      "index": 5,
      "basicDependencies": [
        {
          "dep": "ROOT",
          "governor": 0,
          "governorGloss": "ROOT",
          "dependent": 2,
          "dependentGloss": "rally"
        },
        {
          "dep": "nsubj",
          "governor": 2,
          "governorGloss": "rally",
          "dependent": 1,
          "dependentGloss": "Campaigners"
        },
        {
          "dep": "case",
          "governor": 4,
          "governorGloss": "Commons",
          "dependent": 3,
          "dependentGloss": "outside"
        },
        {
          "dep": "obl",
          "governor": 2,
          "governorGloss": "rally",
          "dependent": 4,
          "dependentGloss": "Commons"
        },
        {
          "dep": "case",
          "governor": 7,
          "governorGloss": "powers",
          "dependent": 5,
          "dependentGloss": "as"
        },
        {
          "dep": "compound",
          "governor": 7,
          "governorGloss": "powers",
          "dependent": 6,
          "dependentGloss": "debate"
        },
        {
          "dep": "obl",
          "governor": 2,
          "governorGloss": "rally",
          "dependent": 7,
          "dependentGloss": "powers"
        },
        {
          "dep": "advmod",
          "governor": 7,
          "governorGloss": "powers",
          "dependent": 8,
          "dependentGloss": "on"
        },
        {
          "dep": "punct",
          "governor": 2,
          "governorGloss": "rally",
          "dependent": 9,
          "dependentGloss": "."
        }
      ],
      "enhancedDependencies": [
        {
          "dep": "ROOT",
          "governor": 0,
          "governorGloss": "ROOT",
          "dependent": 2,
          "dependentGloss": "rally"
        },
        {
          "dep": "nsubj",
          "governor": 2,
          "governorGloss": "rally",
          "dependent": 1,
          "dependentGloss": "Campaigners"
        },
        {
          "dep": "case",
          "governor": 4,
          "governorGloss": "Commons",
          "dependent": 3,
          "dependentGloss": "outside"
        },
        {
          "dep": "obl:outside",
          "governor": 2,
          "governorGloss": "rally",
          "dependent": 4,
          "dependentGloss": "Commons"
        },
        {
          "dep": "case",
          "governor": 7,
          "governorGloss": "powers",
          "dependent": 5,
          "dependentGloss": "as"
        },
        {
          "dep": "compound",
          "governor": 7,
          "governorGloss": "powers",
          "dependent": 6,
          "dependentGloss": "debate"
        },
        {
          "dep": "obl:as",
          "governor": 2,
          "governorGloss": "rally",
          "dependent": 7,
          "dependentGloss": "powers"
        },
        {
          "dep": "advmod",
          "governor": 7,
          "governorGloss": "powers",
          "dependent": 8,
          "dependentGloss": "on"
        },
        {
          "dep": "punct",
          "governor": 2,
          "governorGloss": "rally",
          "dependent": 9,
          "dependentGloss": "."
        }
      ],
      "enhancedPlusPlusDependencies": [
        {
          "dep": "ROOT",
          "governor": 0,
          "governorGloss": "ROOT",
          "dependent": 2,
          "dependentGloss": "rally"
        },
        {
          "dep": "nsubj",
          "governor": 2,
          "governorGloss": "rally",
          "dependent": 1,
          "dependentGloss": "Campaigners"
        },
        {
          "dep": "case",
          "governor": 4,
          "governorGloss": "Commons",
          "dependent": 3,
          "dependentGloss": "outside"
        },
        {
          "dep": "obl:outside",
          "governor": 2,
          "governorGloss": "rally",
          "dependent": 4,
          "dependentGloss": "Commons"
        },
        {
          "dep": "case",
          "governor": 7,
          "governorGloss": "powers",
          "dependent": 5,
          "dependentGloss": "as"
        },
        {
          "dep": "compound",
          "governor": 7,
          "governorGloss": "powers",
          "dependent": 6,
          "dependentGloss": "debate"
        },
        {
          "dep": "obl:as",
          "governor": 2,
          "governorGloss": "rally",
          "dependent": 7,
          "dependentGloss": "powers"
        },
        {
          "dep": "advmod",
          "governor": 7,
          "governorGloss": "powers",
          "dependent": 8,
          "dependentGloss": "on"
        },
        {
          "dep": "punct",
          "governor": 2,
          "governorGloss": "rally",
          "dependent": 9,
          "dependentGloss": "."
        }
      ],
      "entitymentions": [
      ],
      "tokens": [
        {
          "index": 1,
          "word": "Campaigners",
          "originalText": "Campaigners",
          "lemma": "campaigner",
          "characterOffsetBegin": 100,
          "characterOffsetEnd": 111,
          "pos": "NNS",
          "ner": "O",
          "before": " ",
          "after": " "
        },
        {
          "index": 2,
          "word": "rally",
          "originalText": "rally",
          "lemma": "rally",
          "characterOffsetBegin": 112,
          "characterOffsetEnd": 117,
          "pos": "VBP",
          "ner": "O",
          "before": " ",
          "after": " "
        },
        {
          "index": 3,
          "word": "outside",
          "originalText": "outside",
          "lemma": "outside",
          "characterOffsetBegin": 118,
          "characterOffsetEnd": 125,
          "pos": "IN",
          "ner": "O",
          "before": " ",
          "after": " "
        },
        {
          "index": 4,
          "word": "Commons",
          "originalText": "Commons",
          "lemma": "Commons",
          "characterOffsetBegin": 126,
          "characterOffsetEnd": 133,
          "pos": "NNP",
          "ner": "O",
          "before": " ",
          "after": " "
        },
        {
          "index": 5,
          "word": "as",
          "originalText": "as",
          "lemma": "as",
          "characterOffsetBegin": 134,
          "characterOffsetEnd": 136,
          "pos": "IN",
          "ner": "O",
          "before": " ",
          "after": " "
        },
        {
          "index": 6,
          "word": "debate",
          "originalText": "debate",
          "lemma": "debate",
          "characterOffsetBegin": 137,
          "characterOffsetEnd": 143,
          "pos": "NN",
          "ner": "O",
          "before": " ",
          "after": " "
        },
        {
          "index": 7,
          "word": "powers",
          "originalText": "powers",
          "lemma": "power",
          "characterOffsetBegin": 144,
          "characterOffsetEnd": 150,
          "pos": "NNS",
          "ner": "O",
          "before": " ",
          "after": " "
        },
        {
          "index": 8,
          "word": "on",
          "originalText": "on",
          "lemma": "on",
          "characterOffsetBegin": 151,
          "characterOffsetEnd": 153,
          "pos": "IN",
          "ner": "O",
          "before": " ",
          "after": ""
        },
        {
          "index": 9,
          "word": ".",
          "originalText": ".",
          "lemma": ".",
          "characterOffsetBegin": 153,
          "characterOffsetEnd": 154,
          "pos": ".",
          "ner": "O",
          "before": "",
          "after": " "
        }
      ]
    },
    {
      "index": 6,
      "basicDependencies": [
        {
          "dep": "ROOT",
          "governor": 0,
          "governorGloss": "ROOT",
          "dependent": 1,
          "dependentGloss": "T"
        },
        {
          "dep": "punct",
          "governor": 1,
          "governorGloss": "T",
          "dependent": 2,
          "dependentGloss": "-"
        },
        {
          "dep": "compound",
          "governor": 9,
          "governorGloss": "E-E-N-D",
          "dependent": 3,
          "dependentGloss": "I"
        },
        {
          "dep": "punct",
          "governor": 9,
          "governorGloss": "E-E-N-D",
          "dependent": 4,
          "dependentGloss": "-"
        },
        {
          "dep": "compound",
          "governor": 9,
          "governorGloss": "E-E-N-D",
          "dependent": 5,
          "dependentGloss": "T"
        },
        {
          "dep": "punct",
          "governor": 9,
          "governorGloss": "E-E-N-D",
          "dependent": 6,
          "dependentGloss": "-"
        },
        {
          "dep": "compound",
          "governor": 9,
          "governorGloss": "E-E-N-D",
          "dependent": 7,
          "dependentGloss": "L"
        },
        {
          "dep": "punct",
          "governor": 9,
          "governorGloss": "E-E-N-D",
          "dependent": 8,
          "dependentGloss": "-"
        },
        {
          "dep": "dep",
          "governor": 1,
          "governorGloss": "T",
          "dependent": 9,
          "dependentGloss": "E-E-N-D"
        },
        {
          "dep": "punct",
          "governor": 1,
          "governorGloss": "T",
          "dependent": 10,
          "dependentGloss": "."
        }
      ],
      "enhancedDependencies": [
        {
          "dep": "ROOT",
          "governor": 0,
          "governorGloss": "ROOT",
          "dependent": 1,
          "dependentGloss": "T"
        },
        {
          "dep": "punct",
          "governor": 1,
          "governorGloss": "T",
          "dependent": 2,
          "dependentGloss": "-"
        },
        {
          "dep": "compound",
          "governor": 9,
          "governorGloss": "E-E-N-D",
          "dependent": 3,
          "dependentGloss": "I"
        },
        {
          "dep": "punct",
          "governor": 9,
          "governorGloss": "E-E-N-D",
          "dependent": 4,
          "dependentGloss": "-"
        },
        {
          "dep": "compound",
          "governor": 9,
          "governorGloss": "E-E-N-D",
          "dependent": 5,
          "dependentGloss": "T"
        },
        {
          "dep": "punct",
          "governor": 9,
          "governorGloss": "E-E-N-D",
          "dependent": 6,
          "dependentGloss": "-"
        },
        {
          "dep": "compound",
          "governor": 9,
          "governorGloss": "E-E-N-D",
          "dependent": 7,
          "dependentGloss": "L"
        },
        {
          "dep": "punct",
          "governor": 9,
          "governorGloss": "E-E-N-D",
          "dependent": 8,
          "dependentGloss": "-"
        },
        {
          "dep": "dep",
          "governor": 1,
          "governorGloss": "T",
          "dependent": 9,
          "dependentGloss": "E-E-N-D"
        },
        {
          "dep": "punct",
          "governor": 1,
          "governorGloss": "T",
          "dependent": 10,
          "dependentGloss": "."
        }
      ],
      "enhancedPlusPlusDependencies": [
        {
          "dep": "ROOT",
          "governor": 0,
          "governorGloss": "ROOT",
          "dependent": 1,
          "dependentGloss": "T"
        },
        {
          "dep": "punct",
          "governor": 1,
          "governorGloss": "T",
          "dependent": 2,
          "dependentGloss": "-"
        },
        {
          "dep": "compound",
          "governor": 9,
          "governorGloss": "E-E-N-D",
          "dependent": 3,
          "dependentGloss": "I"
        },
        {
          "dep": "punct",
          "governor": 9,
          "governorGloss": "E-E-N-D",
          "dependent": 4,
          "dependentGloss": "-"
        },
        {
          "dep": "compound",
          "governor": 9,
          "governorGloss": "E-E-N-D",
          "dependent": 5,
          "dependentGloss": "T"
        },
        {
          "dep": "punct",
          "governor": 9,
          "governorGloss": "E-E-N-D",
          "dependent": 6,
          "dependentGloss": "-"
        },
        {
          "dep": "compound",
          "governor": 9,
          "governorGloss": "E-E-N-D",
          "dependent": 7,
          "dependentGloss": "L"
        },
        {
          "dep": "punct",
          "governor": 9,
          "governorGloss": "E-E-N-D",
          "dependent": 8,
          "dependentGloss": "-"
        },
        {
          "dep": "dep",
          "governor": 1,
          "governorGloss": "T",
          "dependent": 9,
          "dependentGloss": "E-E-N-D"
        },
        {
          "dep": "punct",
          "governor": 1,
          "governorGloss": "T",
          "dependent": 10,
          "dependentGloss": "."
        }
      ],
      "entitymentions": [
      ],
      "tokens": [
        {
          "index": 1,
          "word": "T",
          "originalText": "T",
          "lemma": "t",
          "characterOffsetBegin": 155,
          "characterOffsetEnd": 156,
          "pos": "NN",
          "ner": "O",
          "before": " ",
          "after": ""
        },
        {
          "index": 2,
          "word": "-",
          "originalText": "-",
          "lemma": "-",
          "characterOffsetBegin": 156,
          "characterOffsetEnd": 157,
          "pos": ":",
          "ner": "O",
          "before": "",
          "after": ""
        },
        {
          "index": 3,
          "word": "I",
          "originalText": "I",
          "lemma": "i",
          "characterOffsetBegin": 157,
          "characterOffsetEnd": 158,
          "pos": "NN",
          "ner": "O",
          "before": "",
          "after": ""
        },
        {
          "index": 4,
          "word": "-",
          "originalText": "-",
          "lemma": "-",
          "characterOffsetBegin": 158,
          "characterOffsetEnd": 159,
          "pos": "HYPH",
          "ner": "O",
          "before": "",
          "after": ""
        },
        {
          "index": 5,
          "word": "T",
          "originalText": "T",
          "lemma": "t",
          "characterOffsetBegin": 159,
          "characterOffsetEnd": 160,
          "pos": "NN",
          "ner": "O",
          "before": "",
          "after": ""
        },
        {
          "index": 6,
          "word": "-",
          "originalText": "-",
          "lemma": "-",
          "characterOffsetBegin": 160,
          "characterOffsetEnd": 161,
          "pos": "HYPH",
          "ner": "O",
          "before": "",
          "after": ""
        },
        {
          "index": 7,
          "word": "L",
          "originalText": "L",
          "lemma": "l",
          "characterOffsetBegin": 161,
          "characterOffsetEnd": 162,
          "pos": "NN",
          "ner": "O",
          "before": "",
          "after": ""
        },
        {
          "index": 8,
          "word": "-",
          "originalText": "-",
          "lemma": "-",
          "characterOffsetBegin": 162,
          "characterOffsetEnd": 163,
          "pos": "HYPH",
          "ner": "O",
          "before": "",
          "after": ""
        },
        {
          "index": 9,
          "word": "E-E-N-D",
          "originalText": "E-E-N-D",
          "lemma": "e-e-n-d",
          "characterOffsetBegin": 163,
          "characterOffsetEnd": 170,
          "pos": "NN",
          "ner": "O",
          "before": "",
          "after": ""
        },
        {
          "index": 10,
          "word": ".",
          "originalText": ".",
          "lemma": ".",
          "characterOffsetBegin": 170,
          "characterOffsetEnd": 171,
          "pos": ".",
          "ner": "O",
          "before": "",
          "after": "  "
        }
      ]
    },
    {
      "index": 7,
      "basicDependencies": [
        {
          "dep": "ROOT",
          "governor": 0,
          "governorGloss": "ROOT",
          "dependent": 3,
          "dependentGloss": "E-X-T-S-T-A-R-T"
        },
        {
          "dep": "compound",
          "governor": 3,
          "governorGloss": "E-X-T-S-T-A-R-T",
          "dependent": 1,
          "dependentGloss": "T"
        },
        {
          "dep": "punct",
          "governor": 3,
          "governorGloss": "E-X-T-S-T-A-R-T",
          "dependent": 2,
          "dependentGloss": "-"
        },
        {
          "dep": "punct",
          "governor": 3,
          "governorGloss": "E-X-T-S-T-A-R-T",
          "dependent": 4,
          "dependentGloss": "."
        }
      ],
      "enhancedDependencies": [
        {
          "dep": "ROOT",
          "governor": 0,
          "governorGloss": "ROOT",
          "dependent": 3,
          "dependentGloss": "E-X-T-S-T-A-R-T"
        },
        {
          "dep": "compound",
          "governor": 3,
          "governorGloss": "E-X-T-S-T-A-R-T",
          "dependent": 1,
          "dependentGloss": "T"
        },
        {
          "dep": "punct",
          "governor": 3,
          "governorGloss": "E-X-T-S-T-A-R-T",
          "dependent": 2,
          "dependentGloss": "-"
        },
        {
          "dep": "punct",
          "governor": 3,
          "governorGloss": "E-X-T-S-T-A-R-T",
          "dependent": 4,
          "dependentGloss": "."
        }
      ],
      "enhancedPlusPlusDependencies": [
        {
          "dep": "ROOT",
          "governor": 0,
          "governorGloss": "ROOT",
          "dependent": 3,
          "dependentGloss": "E-X-T-S-T-A-R-T"
        },
        {
          "dep": "compound",
          "governor": 3,
          "governorGloss": "E-X-T-S-T-A-R-T",
          "dependent": 1,
          "dependentGloss": "T"
        },
        {
          "dep": "punct",
          "governor": 3,
          "governorGloss": "E-X-T-S-T-A-R-T",
          "dependent": 2,
          "dependentGloss": "-"
        },
        {
          "dep": "punct",
          "governor": 3,
          "governorGloss": "E-X-T-S-T-A-R-T",
          "dependent": 4,
          "dependentGloss": "."
        }
      ],
      "entitymentions": [
      ],
      "tokens": [
        {
          "index": 1,
          "word": "T",
          "originalText": "T",
          "lemma": "t",
          "characterOffsetBegin": 173,
          "characterOffsetEnd": 174,
          "pos": "NN",
          "ner": "O",
          "before": "  ",
          "after": ""
        },
        {
          "index": 2,
          "word": "-",
          "originalText": "-",
          "lemma": "-",
          "characterOffsetBegin": 174,
          "characterOffsetEnd": 175,
          "pos": "HYPH",
          "ner": "O",
          "before": "",
          "after": ""
        },
        {
          "index": 3,
          "word": "E-X-T-S-T-A-R-T",
          "originalText": "E-X-T-S-T-A-R-T",
          "lemma": "e-x-t-s-t-a-r-t",
          "characterOffsetBegin": 175,
          "characterOffsetEnd": 190,
          "pos": "NN",
          "ner": "O",
          "before": "",
          "after": ""
        },
        {
          "index": 4,
          "word": ".",
          "originalText": ".",
          "lemma": ".",
          "characterOffsetBegin": 190,
          "characterOffsetEnd": 191,
          "pos": ".",
          "ner": "O",
          "before": "",
          "after": " "
        }
      ]
    },
    {
      "index": 8,
      "basicDependencies": [
        {
          "dep": "ROOT",
          "governor": 0,
          "governorGloss": "ROOT",
          "dependent": 2,
          "dependentGloss": "take"
        },
        {
          "dep": "nsubj",
          "governor": 2,
          "governorGloss": "take",
          "dependent": 1,
          "dependentGloss": "People"
        },
        {
          "dep": "obj",
          "governor": 2,
          "governorGloss": "take",
          "dependent": 3,
          "dependentGloss": "part"
        },
        {
          "dep": "case",
          "governor": 6,
          "governorGloss": "rally",
          "dependent": 4,
          "dependentGloss": "in"
        },
        {
          "dep": "det",
          "governor": 6,
          "governorGloss": "rally",
          "dependent": 5,
          "dependentGloss": "a"
        },
        {
          "dep": "obl",
          "governor": 2,
          "governorGloss": "take",
          "dependent": 6,
          "dependentGloss": "rally"
        },
        {
          "dep": "acl",
          "governor": 6,
          "governorGloss": "rally",
          "dependent": 7,
          "dependentGloss": "organised"
        },
        {
          "dep": "case",
          "governor": 11,
          "governorGloss": "Campaign",
          "dependent": 8,
          "dependentGloss": "by"
        },
        {
          "dep": "compound",
          "governor": 11,
          "governorGloss": "Campaign",
          "dependent": 9,
          "dependentGloss": "Palestine"
        },
        {
          "dep": "compound",
          "governor": 11,
          "governorGloss": "Campaign",
          "dependent": 10,
          "dependentGloss": "Solidarity"
        },
        {
          "dep": "obl",
          "governor": 7,
          "governorGloss": "organised",
          "dependent": 11,
          "dependentGloss": "Campaign"
        },
        {
          "dep": "case",
          "governor": 14,
          "governorGloss": "Houses",
          "dependent": 12,
          "dependentGloss": "outside"
        },
        {
          "dep": "det",
          "governor": 14,
          "governorGloss": "Houses",
          "dependent": 13,
          "dependentGloss": "the"
        },
        {
          "dep": "nmod",
          "governor": 11,
          "governorGloss": "Campaign",
          "dependent": 14,
          "dependentGloss": "Houses"
        },
        {
          "dep": "case",
          "governor": 16,
          "governorGloss": "Parliament",
          "dependent": 15,
          "dependentGloss": "of"
        },
        {
          "dep": "nmod",
          "governor": 14,
          "governorGloss": "Houses",
          "dependent": 16,
          "dependentGloss": "Parliament"
        },
        {
          "dep": "case",
          "governor": 18,
          "governorGloss": "London",
          "dependent": 17,
          "dependentGloss": "in"
        },
        {
          "dep": "nmod",
          "governor": 11,
          "governorGloss": "Campaign",
          "dependent": 18,
          "dependentGloss": "London"
        },
        {
          "dep": "punct",
          "governor": 2,
          "governorGloss": "take",
          "dependent": 19,
          "dependentGloss": ","
        },
        {
          "dep": "mark",
          "governor": 22,
          "governorGloss": "continue",
          "dependent": 20,
          "dependentGloss": "as"
        },
        {
          "dep": "nsubj",
          "governor": 22,
          "governorGloss": "continue",
          "dependent": 21,
          "dependentGloss": "MPs"
        },
        {
          "dep": "advcl",
          "governor": 2,
          "governorGloss": "take",
          "dependent": 22,
          "dependentGloss": "continue"
        },
        {
          "dep": "mark",
          "governor": 24,
          "governorGloss": "debate",
          "dependent": 23,
          "dependentGloss": "to"
        },
        {
          "dep": "xcomp",
          "governor": 22,
          "governorGloss": "continue",
          "dependent": 24,
          "dependentGloss": "debate"
        },
        {
          "dep": "obj",
          "governor": 24,
          "governorGloss": "debate",
          "dependent": 25,
          "dependentGloss": "calls"
        },
        {
          "dep": "case",
          "governor": 28,
          "governorGloss": "ceasefire",
          "dependent": 26,
          "dependentGloss": "for"
        },
        {
          "dep": "det",
          "governor": 28,
          "governorGloss": "ceasefire",
          "dependent": 27,
          "dependentGloss": "a"
        },
        {
          "dep": "nmod",
          "governor": 25,
          "governorGloss": "calls",
          "dependent": 28,
          "dependentGloss": "ceasefire"
        },
        {
          "dep": "case",
          "governor": 30,
          "governorGloss": "Gaza",
          "dependent": 29,
          "dependentGloss": "in"
        },
        {
          "dep": "nmod",
          "governor": 28,
          "governorGloss": "ceasefire",
          "dependent": 30,
          "dependentGloss": "Gaza"
        },
        {
          "dep": "punct",
          "governor": 2,
          "governorGloss": "take",
          "dependent": 31,
          "dependentGloss": "."
        }
      ],
      "enhancedDependencies": [
        {
          "dep": "ROOT",
          "governor": 0,
          "governorGloss": "ROOT",
          "dependent": 2,
          "dependentGloss": "take"
        },
        {
          "dep": "nsubj",
          "governor": 2,
          "governorGloss": "take",
          "dependent": 1,
          "dependentGloss": "People"
        },
        {
          "dep": "obj",
          "governor": 2,
          "governorGloss": "take",
          "dependent": 3,
          "dependentGloss": "part"
        },
        {
          "dep": "case",
          "governor": 6,
          "governorGloss": "rally",
          "dependent": 4,
          "dependentGloss": "in"
        },
        {
          "dep": "det",
          "governor": 6,
          "governorGloss": "rally",
          "dependent": 5,
          "dependentGloss": "a"
        },
        {
          "dep": "obl:in",
          "governor": 2,
          "governorGloss": "take",
          "dependent": 6,
          "dependentGloss": "rally"
        },
        {
          "dep": "acl",
          "governor": 6,
          "governorGloss": "rally",
          "dependent": 7,
          "dependentGloss": "organised"
        },
        {
          "dep": "case",
          "governor": 11,
          "governorGloss": "Campaign",
          "dependent": 8,
          "dependentGloss": "by"
        },
        {
          "dep": "compound",
          "governor": 11,
          "governorGloss": "Campaign",
          "dependent": 9,
          "dependentGloss": "Palestine"
        },
        {
          "dep": "compound",
          "governor": 11,
          "governorGloss": "Campaign",
          "dependent": 10,
          "dependentGloss": "Solidarity"
        },
        {
          "dep": "obl:by",
          "governor": 7,
          "governorGloss": "organised",
          "dependent": 11,
          "dependentGloss": "Campaign"
        },
        {
          "dep": "case",
          "governor": 14,
          "governorGloss": "Houses",
          "dependent": 12,
          "dependentGloss": "outside"
        },
        {
          "dep": "det",
          "governor": 14,
          "governorGloss": "Houses",
          "dependent": 13,
          "dependentGloss": "the"
        },
        {
          "dep": "nmod:outside",
          "governor": 11,
          "governorGloss": "Campaign",
          "dependent": 14,
          "dependentGloss": "Houses"
        },
        {
          "dep": "case",
          "governor": 16,
          "governorGloss": "Parliament",
          "dependent": 15,
          "dependentGloss": "of"
        },
        {
          "dep": "nmod:of",
          "governor": 14,
          "governorGloss": "Houses",
          "dependent": 16,
          "dependentGloss": "Parliament"
        },
        {
          "dep": "case",
          "governor": 18,
          "governorGloss": "London",
          "dependent": 17,
          "dependentGloss": "in"
        },
        {
          "dep": "nmod:in",
          "governor": 11,
          "governorGloss": "Campaign",
          "dependent": 18,
          "dependentGloss": "London"
        },
        {
          "dep": "punct",
          "governor": 2,
          "governorGloss": "take",
          "dependent": 19,
          "dependentGloss": ","
        },
        {
          "dep": "mark",
          "governor": 22,
          "governorGloss": "continue",
          "dependent": 20,
          "dependentGloss": "as"
        },
        {
          "dep": "nsubj",
          "governor": 22,
          "governorGloss": "continue",
          "dependent": 21,
          "dependentGloss": "MPs"
        },
        {
          "dep": "nsubj:xsubj",
          "governor": 24,
          "governorGloss": "debate",
          "dependent": 21,
          "dependentGloss": "MPs"
        },
        {
          "dep": "advcl:as",
          "governor": 2,
          "governorGloss": "take",
          "dependent": 22,
          "dependentGloss": "continue"
        },
        {
          "dep": "mark",
          "governor": 24,
          "governorGloss": "debate",
          "dependent": 23,
          "dependentGloss": "to"
        },
        {
          "dep": "xcomp",
          "governor": 22,
          "governorGloss": "continue",
          "dependent": 24,
          "dependentGloss": "debate"
        },
        {
          "dep": "obj",
          "governor": 24,
          "governorGloss": "debate",
          "dependent": 25,
          "dependentGloss": "calls"
        },
        {
          "dep": "case",
          "governor": 28,
          "governorGloss": "ceasefire",
          "dependent": 26,
          "dependentGloss": "for"
        },
        {
          "dep": "det",
          "governor": 28,
          "governorGloss": "ceasefire",
          "dependent": 27,
          "dependentGloss": "a"
        },
        {
          "dep": "nmod:for",
          "governor": 25,
          "governorGloss": "calls",
          "dependent": 28,
          "dependentGloss": "ceasefire"
        },
        {
          "dep": "case",
          "governor": 30,
          "governorGloss": "Gaza",
          "dependent": 29,
          "dependentGloss": "in"
        },
        {
          "dep": "nmod:in",
          "governor": 28,
          "governorGloss": "ceasefire",
          "dependent": 30,
          "dependentGloss": "Gaza"
        },
        {
          "dep": "punct",
          "governor": 2,
          "governorGloss": "take",
          "dependent": 31,
          "dependentGloss": "."
        }
      ],
      "enhancedPlusPlusDependencies": [
        {
          "dep": "ROOT",
          "governor": 0,
          "governorGloss": "ROOT",
          "dependent": 2,
          "dependentGloss": "take"
        },
        {
          "dep": "nsubj",
          "governor": 2,
          "governorGloss": "take",
          "dependent": 1,
          "dependentGloss": "People"
        },
        {
          "dep": "obj",
          "governor": 2,
          "governorGloss": "take",
          "dependent": 3,
          "dependentGloss": "part"
        },
        {
          "dep": "case",
          "governor": 6,
          "governorGloss": "rally",
          "dependent": 4,
          "dependentGloss": "in"
        },
        {
          "dep": "det",
          "governor": 6,
          "governorGloss": "rally",
          "dependent": 5,
          "dependentGloss": "a"
        },
        {
          "dep": "obl:in",
          "governor": 2,
          "governorGloss": "take",
          "dependent": 6,
          "dependentGloss": "rally"
        },
        {
          "dep": "acl",
          "governor": 6,
          "governorGloss": "rally",
          "dependent": 7,
          "dependentGloss": "organised"
        },
        {
          "dep": "case",
          "governor": 11,
          "governorGloss": "Campaign",
          "dependent": 8,
          "dependentGloss": "by"
        },
        {
          "dep": "compound",
          "governor": 11,
          "governorGloss": "Campaign",
          "dependent": 9,
          "dependentGloss": "Palestine"
        },
        {
          "dep": "compound",
          "governor": 11,
          "governorGloss": "Campaign",
          "dependent": 10,
          "dependentGloss": "Solidarity"
        },
        {
          "dep": "obl:by",
          "governor": 7,
          "governorGloss": "organised",
          "dependent": 11,
          "dependentGloss": "Campaign"
        },
        {
          "dep": "case",
          "governor": 14,
          "governorGloss": "Houses",
          "dependent": 12,
          "dependentGloss": "outside"
        },
        {
          "dep": "det",
          "governor": 14,
          "governorGloss": "Houses",
          "dependent": 13,
          "dependentGloss": "the"
        },
        {
          "dep": "nmod:outside",
          "governor": 11,
          "governorGloss": "Campaign",
          "dependent": 14,
          "dependentGloss": "Houses"
        },
        {
          "dep": "case",
          "governor": 16,
          "governorGloss": "Parliament",
          "dependent": 15,
          "dependentGloss": "of"
        },
        {
          "dep": "nmod:of",
          "governor": 14,
          "governorGloss": "Houses",
          "dependent": 16,
          "dependentGloss": "Parliament"
        },
        {
          "dep": "case",
          "governor": 18,
          "governorGloss": "London",
          "dependent": 17,
          "dependentGloss": "in"
        },
        {
          "dep": "nmod:in",
          "governor": 11,
          "governorGloss": "Campaign",
          "dependent": 18,
          "dependentGloss": "London"
        },
        {
          "dep": "punct",
          "governor": 2,
          "governorGloss": "take",
          "dependent": 19,
          "dependentGloss": ","
        },
        {
          "dep": "mark",
          "governor": 22,
          "governorGloss": "continue",
          "dependent": 20,
          "dependentGloss": "as"
        },
        {
          "dep": "nsubj",
          "governor": 22,
          "governorGloss": "continue",
          "dependent": 21,
          "dependentGloss": "MPs"
        },
        {
          "dep": "nsubj:xsubj",
          "governor": 24,
          "governorGloss": "debate",
          "dependent": 21,
          "dependentGloss": "MPs"
        },
        {
          "dep": "advcl:as",
          "governor": 2,
          "governorGloss": "take",
          "dependent": 22,
          "dependentGloss": "continue"
        },
        {
          "dep": "mark",
          "governor": 24,
          "governorGloss": "debate",
          "dependent": 23,
          "dependentGloss": "to"
        },
        {
          "dep": "xcomp",
          "governor": 22,
          "governorGloss": "continue",
          "dependent": 24,
          "dependentGloss": "debate"
        },
        {
          "dep": "obj",
          "governor": 24,
          "governorGloss": "debate",
          "dependent": 25,
          "dependentGloss": "calls"
        },
        {
          "dep": "case",
          "governor": 28,
          "governorGloss": "ceasefire",
          "dependent": 26,
          "dependentGloss": "for"
        },
        {
          "dep": "det",
          "governor": 28,
          "governorGloss": "ceasefire",
          "dependent": 27,
          "dependentGloss": "a"
        },
        {
          "dep": "nmod:for",
          "governor": 25,
          "governorGloss": "calls",
          "dependent": 28,
          "dependentGloss": "ceasefire"
        },
        {
          "dep": "case",
          "governor": 30,
          "governorGloss": "Gaza",
          "dependent": 29,
          "dependentGloss": "in"
        },
        {
          "dep": "nmod:in",
          "governor": 28,
          "governorGloss": "ceasefire",
          "dependent": 30,
          "dependentGloss": "Gaza"
        },
        {
          "dep": "punct",
          "governor": 2,
          "governorGloss": "take",
          "dependent": 31,
          "dependentGloss": "."
        }
      ],
      "entitymentions": [
        {
          "docTokenBegin": 67,
          "docTokenEnd": 69,
          "tokenBegin": 8,
          "tokenEnd": 10,
          "text": "Palestine Solidarity",
          "characterOffsetBegin": 233,
          "characterOffsetEnd": 253,
          "ner": "ORGANIZATION",
          "nerConfidences": {
            "ORGANIZATION": 0.97079680327665
          }
        },
        {
          "docTokenBegin": 72,
          "docTokenEnd": 75,
          "tokenBegin": 13,
          "tokenEnd": 16,
          "text": "Houses of Parliament",
          "characterOffsetBegin": 275,
          "characterOffsetEnd": 295,
          "ner": "ORGANIZATION",
          "nerConfidences": {
            "ORGANIZATION": 0.67449424696308
          }
        },
        {
          "docTokenBegin": 76,
          "docTokenEnd": 77,
          "tokenBegin": 17,
          "tokenEnd": 18,
          "text": "London",
          "characterOffsetBegin": 299,
          "characterOffsetEnd": 305,
          "ner": "CITY",
          "nerConfidences": {
            "LOCATION": 0.99424284923322
          }
        },
        {
          "docTokenBegin": 88,
          "docTokenEnd": 89,
          "tokenBegin": 29,
          "tokenEnd": 30,
          "text": "Gaza",
          "characterOffsetBegin": 358,
          "characterOffsetEnd": 362,
          "ner": "LOCATION",
          "nerConfidences": {
            "LOCATION": 0.99948940361075
          }
        }
      ],
      "tokens": [
        {
          "index": 1,
          "word": "People",
          "originalText": "People",
          "lemma": "person",
          "characterOffsetBegin": 192,
          "characterOffsetEnd": 198,
          "pos": "NNS",
          "ner": "O",
          "before": " ",
          "after": " "
        },
        {
          "index": 2,
          "word": "take",
          "originalText": "take",
          "lemma": "take",
          "characterOffsetBegin": 199,
          "characterOffsetEnd": 203,
          "pos": "VBP",
          "ner": "O",
          "before": " ",
          "after": " "
        },
        {
          "index": 3,
          "word": "part",
          "originalText": "part",
          "lemma": "part",
          "characterOffsetBegin": 204,
          "characterOffsetEnd": 208,
          "pos": "NN",
          "ner": "O",
          "before": " ",
          "after": " "
        },
        {
          "index": 4,
          "word": "in",
          "originalText": "in",
          "lemma": "in",
          "characterOffsetBegin": 209,
          "characterOffsetEnd": 211,
          "pos": "IN",
          "ner": "O",
          "before": " ",
          "after": " "
        },
        {
          "index": 5,
          "word": "a",
          "originalText": "a",
          "lemma": "a",
          "characterOffsetBegin": 212,
          "characterOffsetEnd": 213,
          "pos": "DT",
          "ner": "O",
          "before": " ",
          "after": " "
        },
        {
          "index": 6,
          "word": "rally",
          "originalText": "rally",
          "lemma": "rally",
          "characterOffsetBegin": 214,
          "characterOffsetEnd": 219,
          "pos": "NN",
          "ner": "O",
          "before": " ",
          "after": " "
        },
        {
          "index": 7,
          "word": "organised",
          "originalText": "organised",
          "lemma": "organise",
          "characterOffsetBegin": 220,
          "characterOffsetEnd": 229,
          "pos": "VBN",
          "ner": "O",
          "before": " ",
          "after": " "
        },
        {
          "index": 8,
          "word": "by",
          "originalText": "by",
          "lemma": "by",
          "characterOffsetBegin": 230,
          "characterOffsetEnd": 232,
          "pos": "IN",
          "ner": "O",
          "before": " ",
          "after": " "
        },
        {
          "index": 9,
          "word": "Palestine",
          "originalText": "Palestine",
          "lemma": "Palestine",
          "characterOffsetBegin": 233,
          "characterOffsetEnd": 242,
          "pos": "NNP",
          "ner": "ORGANIZATION",
          "before": " ",
          "after": " "
        },
        {
          "index": 10,
          "word": "Solidarity",
          "originalText": "Solidarity",
          "lemma": "Solidarity",
          "characterOffsetBegin": 243,
          "characterOffsetEnd": 253,
          "pos": "NNP",
          "ner": "ORGANIZATION",
          "before": " ",
          "after": " "
        },
        {
          "index": 11,
          "word": "Campaign",
          "originalText": "Campaign",
          "lemma": "Campaign",
          "characterOffsetBegin": 254,
          "characterOffsetEnd": 262,
          "pos": "NNP",
          "ner": "O",
          "before": " ",
          "after": " "
        },
        {
          "index": 12,
          "word": "outside",
          "originalText": "outside",
          "lemma": "outside",
          "characterOffsetBegin": 263,
          "characterOffsetEnd": 270,
          "pos": "IN",
          "ner": "O",
          "before": " ",
          "after": " "
        },
        {
          "index": 13,
          "word": "the",
          "originalText": "the",
          "lemma": "the",
          "characterOffsetBegin": 271,
          "characterOffsetEnd": 274,
          "pos": "DT",
          "ner": "O",
          "before": " ",
          "after": " "
        },
        {
          "index": 14,
          "word": "Houses",
          "originalText": "Houses",
          "lemma": "Houses",
          "characterOffsetBegin": 275,
          "characterOffsetEnd": 281,
          "pos": "NNP",
          "ner": "ORGANIZATION",
          "before": " ",
          "after": " "
        },
        {
          "index": 15,
          "word": "of",
          "originalText": "of",
          "lemma": "of",
          "characterOffsetBegin": 282,
          "characterOffsetEnd": 284,
          "pos": "IN",
          "ner": "ORGANIZATION",
          "before": " ",
          "after": " "
        },
        {
          "index": 16,
          "word": "Parliament",
          "originalText": "Parliament",
          "lemma": "Parliament",
          "characterOffsetBegin": 285,
          "characterOffsetEnd": 295,
          "pos": "NNP",
          "ner": "ORGANIZATION",
          "before": " ",
          "after": " "
        },
        {
          "index": 17,
          "word": "in",
          "originalText": "in",
          "lemma": "in",
          "characterOffsetBegin": 296,
          "characterOffsetEnd": 298,
          "pos": "IN",
          "ner": "O",
          "before": " ",
          "after": " "
        },
        {
          "index": 18,
          "word": "London",
          "originalText": "London",
          "lemma": "London",
          "characterOffsetBegin": 299,
          "characterOffsetEnd": 305,
          "pos": "NNP",
          "ner": "CITY",
          "before": " ",
          "after": ""
        },
        {
          "index": 19,
          "word": ",",
          "originalText": ",",
          "lemma": ",",
          "characterOffsetBegin": 305,
          "characterOffsetEnd": 306,
          "pos": ",",
          "ner": "O",
          "before": "",
          "after": " "
        },
        {
          "index": 20,
          "word": "as",
          "originalText": "as",
          "lemma": "as",
          "characterOffsetBegin": 307,
          "characterOffsetEnd": 309,
          "pos": "IN",
          "ner": "O",
          "before": " ",
          "after": " "
        },
        {
          "index": 21,
          "word": "MPs",
          "originalText": "MPs",
          "lemma": "mp",
          "characterOffsetBegin": 310,
          "characterOffsetEnd": 313,
          "pos": "NNS",
          "ner": "O",
          "before": " ",
          "after": " "
        },
        {
          "index": 22,
          "word": "continue",
          "originalText": "continue",
          "lemma": "continue",
          "characterOffsetBegin": 314,
          "characterOffsetEnd": 322,
          "pos": "VBP",
          "ner": "O",
          "before": " ",
          "after": " "
        },
        {
          "index": 23,
          "word": "to",
          "originalText": "to",
          "lemma": "to",
          "characterOffsetBegin": 323,
          "characterOffsetEnd": 325,
          "pos": "TO",
          "ner": "O",
          "before": " ",
          "after": " "
        },
        {
          "index": 24,
          "word": "debate",
          "originalText": "debate",
          "lemma": "debate",
          "characterOffsetBegin": 326,
          "characterOffsetEnd": 332,
          "pos": "VB",
          "ner": "O",
          "before": " ",
          "after": " "
        },
        {
          "index": 25,
          "word": "calls",
          "originalText": "calls",
          "lemma": "call",
          "characterOffsetBegin": 333,
          "characterOffsetEnd": 338,
          "pos": "NNS",
          "ner": "O",
          "before": " ",
          "after": " "
        },
        {
          "index": 26,
          "word": "for",
          "originalText": "for",
          "lemma": "for",
          "characterOffsetBegin": 339,
          "characterOffsetEnd": 342,
          "pos": "IN",
          "ner": "O",
          "before": " ",
          "after": " "
        },
        {
          "index": 27,
          "word": "a",
          "originalText": "a",
          "lemma": "a",
          "characterOffsetBegin": 343,
          "characterOffsetEnd": 344,
          "pos": "DT",
          "ner": "O",
          "before": " ",
          "after": " "
        },
        {
          "index": 28,
          "word": "ceasefire",
          "originalText": "ceasefire",
          "lemma": "ceasefire",
          "characterOffsetBegin": 345,
          "characterOffsetEnd": 354,
          "pos": "NN",
          "ner": "O",
          "before": " ",
          "after": " "
        },
        {
          "index": 29,
          "word": "in",
          "originalText": "in",
          "lemma": "in",
          "characterOffsetBegin": 355,
          "characterOffsetEnd": 357,
          "pos": "IN",
          "ner": "O",
          "before": " ",
          "after": " "
        },
        {
          "index": 30,
          "word": "Gaza",
          "originalText": "Gaza",
          "lemma": "Gaza",
          "characterOffsetBegin": 358,
          "characterOffsetEnd": 362,
          "pos": "NNP",
          "ner": "LOCATION",
          "before": " ",
          "after": ""
        },
        {
          "index": 31,
          "word": ".",
          "originalText": ".",
          "lemma": ".",
          "characterOffsetBegin": 362,
          "characterOffsetEnd": 363,
          "pos": ".",
          "ner": "O",
          "before": "",
          "after": " "
        }
      ]
    },
    {
      "index": 9,
      "basicDependencies": [
        {
          "dep": "ROOT",
          "governor": 0,
          "governorGloss": "ROOT",
          "dependent": 3,
          "dependentGloss": "E-X-T-E-N-D"
        },
        {
          "dep": "compound",
          "governor": 3,
          "governorGloss": "E-X-T-E-N-D",
          "dependent": 1,
          "dependentGloss": "T"
        },
        {
          "dep": "punct",
          "governor": 3,
          "governorGloss": "E-X-T-E-N-D",
          "dependent": 2,
          "dependentGloss": "-"
        },
        {
          "dep": "punct",
          "governor": 3,
          "governorGloss": "E-X-T-E-N-D",
          "dependent": 4,
          "dependentGloss": "."
        }
      ],
      "enhancedDependencies": [
        {
          "dep": "ROOT",
          "governor": 0,
          "governorGloss": "ROOT",
          "dependent": 3,
          "dependentGloss": "E-X-T-E-N-D"
        },
        {
          "dep": "compound",
          "governor": 3,
          "governorGloss": "E-X-T-E-N-D",
          "dependent": 1,
          "dependentGloss": "T"
        },
        {
          "dep": "punct",
          "governor": 3,
          "governorGloss": "E-X-T-E-N-D",
          "dependent": 2,
          "dependentGloss": "-"
        },
        {
          "dep": "punct",
          "governor": 3,
          "governorGloss": "E-X-T-E-N-D",
          "dependent": 4,
          "dependentGloss": "."
        }
      ],
      "enhancedPlusPlusDependencies": [
        {
          "dep": "ROOT",
          "governor": 0,
          "governorGloss": "ROOT",
          "dependent": 3,
          "dependentGloss": "E-X-T-E-N-D"
        },
        {
          "dep": "compound",
          "governor": 3,
          "governorGloss": "E-X-T-E-N-D",
          "dependent": 1,
          "dependentGloss": "T"
        },
        {
          "dep": "punct",
          "governor": 3,
          "governorGloss": "E-X-T-E-N-D",
          "dependent": 2,
          "dependentGloss": "-"
        },
        {
          "dep": "punct",
          "governor": 3,
          "governorGloss": "E-X-T-E-N-D",
          "dependent": 4,
          "dependentGloss": "."
        }
      ],
      "entitymentions": [
      ],
      "tokens": [
        {
          "index": 1,
          "word": "T",
          "originalText": "T",
          "lemma": "t",
          "characterOffsetBegin": 364,
          "characterOffsetEnd": 365,
          "pos": "NN",
          "ner": "O",
          "before": " ",
          "after": ""
        },
        {
          "index": 2,
          "word": "-",
          "originalText": "-",
          "lemma": "-",
          "characterOffsetBegin": 365,
          "characterOffsetEnd": 366,
          "pos": "HYPH",
          "ner": "O",
          "before": "",
          "after": ""
        },
        {
          "index": 3,
          "word": "E-X-T-E-N-D",
          "originalText": "E-X-T-E-N-D",
          "lemma": "e-x-t-e-n-d",
          "characterOffsetBegin": 366,
          "characterOffsetEnd": 377,
          "pos": "NN",
          "ner": "O",
          "before": "",
          "after": ""
        },
        {
          "index": 4,
          "word": ".",
          "originalText": ".",
          "lemma": ".",
          "characterOffsetBegin": 377,
          "characterOffsetEnd": 378,
          "pos": ".",
          "ner": "O",
          "before": "",
          "after": " "
        }
      ]
    }
  ]
}
